{
  "type": "siegemachines:siege_workbench",
  "pattern": [
    " bs",
    "pBi",
    "lr "
  ],
  "key": {
    "B": {
      "type": "siegemachines:count",
      "base": {
        "item": "siegemachines:turret_base"
      },
      "count": 5
    },
    "b": {
      "type": "siegemachines:count",
      "base" : {
        "item": "siegemachines:beam"
      },
      "count": 8
    },
    "p": {
      "type": "siegemachines:count",
      "base": {
        "tag": "minecraft:planks"
      },
      "count": 2
    },
    "i": {
      "type": "siegemachines:count",
      "base": {
        "tag": "c:ingots/iron"
      },
      "count": 8
    },
    "s": {
      "type": "siegemachines:count",
      "base": {
      "item": "minecraft:string",
        "count": 3
      }
    },
    "l": {
      "item": "minecraft:leather",
      "count": 1
    },
    "r": {
      "type": "siegemachines:count",
      "base": {
        "tag": "c:rods/wooden"
      },
      "count": 4
    }
  },
  "result": {
    "id": "siegemachines:ballista",
    "count": 1
  }
}